mne_features/__init__.py
mne_features/bivariate.py
mne_features/feature_extraction.py
mne_features/mock_numba.py
mne_features/univariate.py
mne_features/utils.py
mne_features-0.3.dist-info/LICENSE
mne_features-0.3.dist-info/METADATA
mne_features-0.3.dist-info/WHEEL
mne_features-0.3.dist-info/top_level.txt
mne_features-0.3.dist-info/RECORD
