Metadata-Version: 2.1
Name: mne-features
Version: 0.3
Summary: MNE-Features software for extracting features from multivariate time series
Download-URL: https://github.com/mne-tools/mne-features.git
Maintainer: Jean-Baptiste Schiratti
Maintainer-email: jean.baptiste.schiratti@gmail.com
License: BSD (3-clause)
Platform: any
Classifier: Intended Audience :: Science/Research
Classifier: Intended Audience :: Developers
Classifier: License :: OSI Approved
Classifier: Programming Language :: Python
Classifier: Topic :: Software Development
Classifier: Topic :: Scientific/Engineering
Classifier: Operating System :: Microsoft :: Windows
Classifier: Operating System :: POSIX
Classifier: Operating System :: Unix
Classifier: Operating System :: MacOS
Classifier: Programming Language :: Python :: 3
Requires-Python: >=3.6
License-File: LICENSE
